[
  {
    "name": "Taxonomy - Single select",
    "description": "Description!!",
    "field_type": "string",
    "allow_list_id": "plu_84f4fc75-d843-48de-bf89-f88e5591cae9",
    "resource_type": "data category",
    "field_definition": null,
    "active": false,
    "id": "plu_1850be9e-fabc-424d-8224-2fc44c84605a"
  },
  {
    "name": "Taxonomy - Multiple select",
    "description": "Anotha one",
    "field_type": "string",
    "allow_list_id": "plu_84f4fc75-d843-48de-bf89-f88e5591cae9",
    "resource_type": "data category",
    "field_definition": null,
    "active": false,
    "id": "plu_71634679-2353-4b80-b291-b9efaba0e7ef"
  },
  {
    "name": "Single select list",
    "description": "Hello",
    "field_type": "string",
    "allow_list_id": "plu_84f4fc75-d843-48de-bf89-f88e5591cae9",
    "resource_type": "system",
    "field_definition": null,
    "active": true,
    "id": "plu_cce3d8da-1a86-492a-b81e-decb279f7384"
  },
  {
    "name": "Multiple select list",
    "description": "world",
    "field_type": "string[]",
    "allow_list_id": "plu_84f4fc75-d843-48de-bf89-f88e5591cae9",
    "resource_type": "system",
    "field_definition": null,
    "active": true,
    "id": "plu_d77fd34a-c708-4478-a80b-bc0e677e8697"
  }
]
